nbtest/__init__.py
nbtest/conftest.py
nbtest/cover.py
nbtest/kernel.py
nbtest/nbtest.py
nbtest_plugin-0.1.6.dist-info/METADATA
nbtest_plugin-0.1.6.dist-info/WHEEL
nbtest_plugin-0.1.6.dist-info/entry_points.txt
nbtest_plugin-0.1.6.dist-info/RECORD
