Metadata-Version: 2.4
Name: nbtest_plugin
Version: 0.1.6
Summary: Pytest plugin for testing Jupyter Notebooks
Classifier: Framework :: Pytest
Requires-Dist: coverage
Requires-Dist: jupyter
Requires-Dist: nbformat
Requires-Dist: numpy
Requires-Dist: pandas
Requires-Dist: pytest
Requires-Dist: pytest-cov
